src/verilog/Xor.v
module Xor(out, a, b);

    output out;
    input a, b;
    wire w0, w1, w2;

    nand nand0(w0, a, b);
    nand nand1(w1, a, w0);
    nand nand2(w2, w0, b);
    nand nand3(out, w1, w2);

endmodule

src/verilog/FullAdder.v
module FullAdder(sum, carry, a, b, cin);

    output sum, carry;
    input a, b, cin;
    wire g0_out, g2_out, g3_out;

    Xor g0(g0_out, a, b);
    Xor g1(sum, g0_out, cin);
    nand g2(g2_out, g0_out, cin);
    nand g3(g3_out, a, b);
    nand g4(carry, g2_out, g3_out);

endmodule

src/verilog/FullAdder_test.v
module FullAdder_test;

    reg a, b, cin;
    wire sum, carry;

    initial
        begin
            $dumpfile("FullAdder_test.vcd");
            $dumpvars(0, fullAdder);
            $monitor("a = %b, b = %b, cin = %b, sum = %b, carry = %b", a, b, cin, sum, carry);

            #1 a = 1'b0; b = 1'b0; cin = 1'b0;
            #1                     cin = 1'b1;
            #1           b = 1'b1; cin = 1'b0;
            #1                     cin = 1'b1;
            #1 a = 1'b1; b = 1'b0; cin = 1'b0;
            #1                     cin = 1'b1;
            #1           b = 1'b1; cin = 1'b0;
            #1                     cin = 1'b1;
            #1 $finish;
        end

    FullAdder fullAdder(sum, carry, a, b, cin);

endmodule

src/verilog/FullAdder_test.vcd
$date
	Sun Dec 22 09:49:16 2019
$end
$version
	Icarus Verilog
$end
$timescale
	1s
$end
$scope module FullAdder_test $end
$scope module fullAdder $end
$var wire 1 ! a $end
$var wire 1 " b $end
$var wire 1 # carry $end
$var wire 1 $ cin $end
$var wire 1 % g0_out $end
$var wire 1 & g2_out $end
$var wire 1 ' g3_out $end
$var wire 1 ( sum $end
$scope module g0 $end
$var wire 1 ! a $end
$var wire 1 " b $end
$var wire 1 % out $end
$var wire 1 ) w0 $end
$var wire 1 * w1 $end
$var wire 1 + w2 $end
$upscope $end
$scope module g1 $end
$var wire 1 % a $end
$var wire 1 $ b $end
$var wire 1 ( out $end
$var wire 1 , w0 $end
$var wire 1 - w1 $end
$var wire 1 . w2 $end
$upscope $end
$upscope $end
$upscope $end
$enddefinitions $end
#0
$dumpvars
x.
x-
x,
x+
x*
x)
x(
x'
x&
x%
x$
x#
x"
x!
$end
#1
0(
1-
0#
0%
1&
1,
1.
1+
1'
1)
1*
0$
0"
0!
#2
1(
0.
1$
#3
0-
1(
1%
1.
0+
0$
1"
#4
0(
1#
1-
0&
0,
1.
1$
#5
1(
0#
0-
1&
1,
1+
0*
0$
0"
1!
#6
0(
1#
1-
0&
0,
1.
1$
#7
0(
0%
1-
1*
1&
1,
0'
0)
1+
0$
1"
#8
1(
0.
1$
