src/verilog/gate.v
module Not(out, in);

    input in;
    output out;

    nand g(out, in, in);

endmodule


module And(out, a, b);

    input a, b;
    output out;
    wire aNandb;

    nand g0(aNandb, a, b);
    Not  g1(out, aNandb);

endmodule


module Or(out, a, b);

    input a, b;
    output out;
    wire nata, natb;

    Not  g0(nota, a);
    Not  g1(notb, b);
    nand g3(out, nota, notb);

endmodule


module Xor(out, a, b);

    input a, b;
    output out;
    wire aNandb, w0, w1;

    nand g0(aNandb, a, b);
    nand g1(w0, a, aNandb);
    nand g2(w1, aNandb, b);
    nand g3(out, w0, w1);

endmodule


module Or8Way(out, in);

    output out;
    input[7:0] in;
    wire w[5:0];
    wire aOrb, cOrd, eOrf, gOrh, g0Org1, g2Org3;

    Or g0(aOrb, in[0], in[1]);
    Or g1(cOrd, in[2], in[3]);
    Or g2(eOrf, in[4], in[5]);
    Or g3(gOrh, in[6], in[7]);
    Or g4(g0Org1, aOrb, cOrd);
    Or g5(g2Org3, eOrf, gOrh);
    Or g6(out, g0Org1, g2Org3);

endmodule

src/verilog/gate_test.v
`include "gate.v"

module gate_test;

    reg[7:0] in;
    wire aNot, abAnd, abOr, abXor, or8Way;

    Not    g0(aNot,   in[0]);
    And    g1(abAnd,  in[1], in[0]);
    Or     g2(abOr,   in[1], in[0]);
    Xor    g3(abXor,  in[1], in[0]);
    Or8Way g4(or8Way, in);

    initial begin
        $dumpfile("gate_test.vcd");
        $dumpvars(0, g0, g1, g2, g3, g4);
        $monitor("%4dns in = %d, aNot = %b, abAnd = %b, abOr = %b, abXor = %b, or8Way = %b", $stime, in, aNot, abAnd, abOr, abXor, or8Way);

        in = 8'b1111_1111;
    end

    always #1 begin
        in = in + 1;
    end

    initial #9 $finish;

endmodule

src/verilog/gate_test.vcd
$date
	Thu Mar  5 22:11:37 2020
$end
$version
	Icarus Verilog
$end
$timescale
	1s
$end
$scope module gate_test $end
$scope module g0 $end
$var wire 1 ! in $end
$var wire 1 " out $end
$upscope $end
$upscope $end
$scope module gate_test $end
$scope module g1 $end
$var wire 1 # a $end
$var wire 1 $ aNandb $end
$var wire 1 % b $end
$var wire 1 & out $end
$scope module g1 $end
$var wire 1 $ in $end
$var wire 1 & out $end
$upscope $end
$upscope $end
$upscope $end
$scope module gate_test $end
$scope module g2 $end
$var wire 1 ' a $end
$var wire 1 ( b $end
$var wire 1 ) nota $end
$var wire 1 * notb $end
$var wire 1 + out $end
$scope module g0 $end
$var wire 1 ' in $end
$var wire 1 ) out $end
$upscope $end
$scope module g1 $end
$var wire 1 ( in $end
$var wire 1 * out $end
$upscope $end
$upscope $end
$upscope $end
$scope module gate_test $end
$scope module g3 $end
$var wire 1 , a $end
$var wire 1 - aNandb $end
$var wire 1 . b $end
$var wire 1 / out $end
$var wire 1 0 w0 $end
$var wire 1 1 w1 $end
$upscope $end
$upscope $end
$scope module gate_test $end
$scope module g4 $end
$var wire 1 2 aOrb $end
$var wire 1 3 cOrd $end
$var wire 1 4 eOrf $end
$var wire 1 5 g0Org1 $end
$var wire 1 6 g2Org3 $end
$var wire 1 7 gOrh $end
$var wire 8 8 in [7:0] $end
$var wire 1 9 out $end
$scope module g0 $end
$var wire 1 : a $end
$var wire 1 ; b $end
$var wire 1 < nota $end
$var wire 1 = notb $end
$var wire 1 2 out $end
$scope module g0 $end
$var wire 1 : in $end
$var wire 1 < out $end
$upscope $end
$scope module g1 $end
$var wire 1 ; in $end
$var wire 1 = out $end
$upscope $end
$upscope $end
$scope module g1 $end
$var wire 1 > a $end
$var wire 1 ? b $end
$var wire 1 @ nota $end
$var wire 1 A notb $end
$var wire 1 3 out $end
$scope module g0 $end
$var wire 1 > in $end
$var wire 1 @ out $end
$upscope $end
$scope module g1 $end
$var wire 1 ? in $end
$var wire 1 A out $end
$upscope $end
$upscope $end
$scope module g2 $end
$var wire 1 B a $end
$var wire 1 C b $end
$var wire 1 D nota $end
$var wire 1 E notb $end
$var wire 1 4 out $end
$scope module g0 $end
$var wire 1 B in $end
$var wire 1 D out $end
$upscope $end
$scope module g1 $end
$var wire 1 C in $end
$var wire 1 E out $end
$upscope $end
$upscope $end
$scope module g3 $end
$var wire 1 F a $end
$var wire 1 G b $end
$var wire 1 H nota $end
$var wire 1 I notb $end
$var wire 1 7 out $end
$scope module g0 $end
$var wire 1 F in $end
$var wire 1 H out $end
$upscope $end
$scope module g1 $end
$var wire 1 G in $end
$var wire 1 I out $end
$upscope $end
$upscope $end
$scope module g4 $end
$var wire 1 2 a $end
$var wire 1 3 b $end
$var wire 1 J nota $end
$var wire 1 K notb $end
$var wire 1 5 out $end
$scope module g0 $end
$var wire 1 2 in $end
$var wire 1 J out $end
$upscope $end
$scope module g1 $end
$var wire 1 3 in $end
$var wire 1 K out $end
$upscope $end
$upscope $end
$scope module g5 $end
$var wire 1 4 a $end
$var wire 1 7 b $end
$var wire 1 L nota $end
$var wire 1 M notb $end
$var wire 1 6 out $end
$scope module g0 $end
$var wire 1 4 in $end
$var wire 1 L out $end
$upscope $end
$scope module g1 $end
$var wire 1 7 in $end
$var wire 1 M out $end
$upscope $end
$upscope $end
$scope module g6 $end
$var wire 1 5 a $end
$var wire 1 6 b $end
$var wire 1 N nota $end
$var wire 1 O notb $end
$var wire 1 9 out $end
$scope module g0 $end
$var wire 1 5 in $end
$var wire 1 N out $end
$upscope $end
$scope module g1 $end
$var wire 1 6 in $end
$var wire 1 O out $end
$upscope $end
$upscope $end
$upscope $end
$upscope $end
$enddefinitions $end
#0
$dumpvars
0O
0N
0M
0L
0K
0J
0I
0H
1G
1F
0E
0D
1C
1B
0A
0@
1?
1>
0=
0<
1;
1:
19
b11111111 8
17
16
15
14
13
12
11
10
0/
1.
0-
1,
1+
0*
0)
1(
1'
1&
1%
0$
1#
0"
1!
$end
#1
09
1N
1O
05
06
1J
1K
1L
1M
0&
0+
02
03
04
07
1"
1$
1)
1*
1-
1<
1=
1@
1A
1D
1E
1H
1I
0!
0#
0%
0'
0(
0,
0.
0:
0;
0>
0?
0B
0C
0F
0G
b0 8
#2
19
0N
15
0J
1+
1/
12
0"
0*
01
0<
1!
1%
1(
1.
1:
b1 8
#3
1"
0)
1*
00
11
1<
0=
0!
1#
0%
1'
0(
1,
0.
0:
1;
b10 8
#4
0/
1&
10
0"
0$
0*
0-
11
0<
1!
1%
1(
1.
1:
b11 8
#5
1J
0K
0&
0+
02
13
1"
1$
1)
1*
1-
1<
1=
0@
0!
0#
0%
0'
0(
0,
0.
0:
0;
1>
b100 8
#6
0J
1+
1/
12
0"
0*
01
0<
1!
1%
1(
1.
1:
b101 8
#7
1"
0)
1*
00
11
1<
0=
0!
1#
0%
1'
0(
1,
0.
0:
1;
b110 8
#8
0/
1&
10
0"
0$
0*
0-
11
0<
1!
1%
1(
1.
1:
b111 8
#9
1J
0&
0+
02
1"
1$
1)
1*
1-
1<
1=
1@
0A
0!
0#
0%
0'
0(
0,
0.
0:
0;
0>
1?
b1000 8
