src/verilog/gate.v
module Not(out, in);

    input in;
    output out;

    nand nand0(out, in, in);

endmodule


module And(out, a, b);

    output out;
    input a, b;
    wire w;

    nand nand0(w, a, b);
    Not not0(out, w);

endmodule


module Or(out, a, b);

    output out;
    input a, b;
    wire w0, w1;

    Not not0(w0, a);
    Not not1(w1, b);
    nand nand0(out, w0, w1);

endmodule


module Xor(out, a, b);

    output out;
    input a, b;
    wire w0, w1, w2;

    nand nand0(w0, a, b);
    nand nand1(w1, a, w0);
    nand nand2(w2, w0, b);
    nand nand3(out, w1, w2);

endmodule


module Or8Way(out, in);

    output out;
    input[7:0] in;
    wire w[5:0];

    Or or0(w0, in[0], in[1]);
    Or or1(w1, in[2], in[3]);
    Or or2(w2, in[4], in[5]);
    Or or3(w3, in[6], in[7]);
    Or or4(w4, w0, w1);
    Or or5(w5, w2, w3);
    Or or6(out, w4, w5);

endmodule

src/verilog/Mux.v
module Mux(out, sel, a, b);

    output out;
    input sel, a, b;
    wire w1, w2, w3;

    Not not1(w1, sel);
    nand nand1(w2, a, w1);
    nand nand2(w3, b, sel);
    nand nand3(out, w2, w3);

endmodule

src/verilog/Mux_test.v
module Mux_test;

    reg sel, a, b;
    wire out;

    initial
        begin
            $dumpfile("Mux_test.vcd");
            $dumpvars(0, mux1);
            $monitor("sel = %b, a = %b, b = %b, out = %b", sel, a, b, out);

            #1 sel = 1'b0; a = 1'b0; b = 1'b0;
            #1 sel = 1'b0; a = 1'b0; b = 1'b1;
            #1 sel = 1'b0; a = 1'b1; b = 1'b0;
            #1 sel = 1'b0; a = 1'b1; b = 1'b1;
            #1 sel = 1'b1; a = 1'b0; b = 1'b0;
            #1 sel = 1'b1; a = 1'b0; b = 1'b1;
            #1 sel = 1'b1; a = 1'b1; b = 1'b0;
            #1 sel = 1'b1; a = 1'b1; b = 1'b1;
            #1 $finish;
        end

    Mux mux1(out, sel, a , b);

endmodule

src/verilog/Mux_test.vcd
$date
	Sun Dec  8 08:14:01 2019
$end
$version
	Icarus Verilog
$end
$timescale
	1s
$end
$scope module Mux_test $end
$scope module mux1 $end
$var wire 1 ! a $end
$var wire 1 " b $end
$var wire 1 # out $end
$var wire 1 $ sel $end
$var wire 1 % w1 $end
$var wire 1 & w2 $end
$var wire 1 ' w3 $end
$scope module not1 $end
$var wire 1 $ in $end
$var wire 1 % out $end
$upscope $end
$upscope $end
$upscope $end
$enddefinitions $end
#0
$dumpvars
x'
x&
x%
x$
x#
x"
x!
$end
#1
0#
1&
1'
1%
0"
0!
0$
#2
1"
#3
1#
0&
0"
1!
#4
1"
#5
0#
1&
0%
0"
0!
1$
#6
1#
0'
1"
#7
0#
1'
0"
1!
#8
1#
0'
1"
