src/verilog/gate.v
module Not(out, in);

    input in;
    output out;

    nand nand0(out, in, in);

endmodule


module And(out, a, b);

    output out;
    input a, b;
    wire w;

    nand nand0(w, a, b);
    Not not0(out, w);

endmodule


module Or(out, a, b);

    output out;
    input a, b;
    wire w0, w1;

    Not not0(w0, a);
    Not not1(w1, b);
    nand nand0(out, w0, w1);

endmodule


module Xor(out, a, b);

    output out;
    input a, b;
    wire w0, w1, w2;

    nand nand0(w0, a, b);
    nand nand1(w1, a, w0);
    nand nand2(w2, w0, b);
    nand nand3(out, w1, w2);

endmodule


module Or8Way(out, in);

    output out;
    input[7:0] in;
    wire w[5:0];

    Or or0(w0, in[0], in[1]);
    Or or1(w1, in[2], in[3]);
    Or or2(w2, in[4], in[5]);
    Or or3(w3, in[6], in[7]);
    Or or4(w4, w0, w1);
    Or or5(w5, w2, w3);
    Or or6(out, w4, w5);

endmodule

src/verilog/Not16.v
module Not16(out, in);

    output[15:0] out;
    input[15:0] in;

    Not not0(out[0], in[0]);
    Not not1(out[1], in[1]);
    Not not2(out[2], in[2]);
    Not not3(out[3], in[3]);
    Not not4(out[4], in[4]);
    Not not5(out[5], in[5]);
    Not not6(out[6], in[6]);
    Not not7(out[7], in[7]);
    Not not8(out[8], in[8]);
    Not not9(out[9], in[9]);
    Not not10(out[10], in[10]);
    Not not11(out[11], in[11]);
    Not not12(out[12], in[12]);
    Not not13(out[13], in[13]);
    Not not14(out[14], in[14]);
    Not not15(out[15], in[15]);

endmodule

src/verilog/Not16_test.v
module Not16_test;

    reg[15:0] in;
    wire[15:0] out;

    initial
        begin
            $dumpfile("Not16_test.vcd");
            $dumpvars(0, not16);
            $monitor("in = %b, out = %b", in, out);

            #1 in = 16'b0000000000000000;
            #1 in = 16'b1111111111111111;
            #1 in = 16'b0000000011111111;
            #1 in = 16'b1111111100000000;
            #1 in = 16'b0000111100001111;
            #1 in = 16'b1111000011110000;
            #1 in = 16'b0011001100110011;
            #1 in = 16'b1100110011001100;
            #1 in = 16'b0101010101010101;
            #1 in = 16'b1010101010101010;
            #1 $finish;
        end

    Not16 not16(out, in);

endmodule

src/verilog/Not16_test.vcd
$date
	Sun Dec  8 21:40:04 2019
$end
$version
	Icarus Verilog
$end
$timescale
	1s
$end
$scope module Not16_test $end
$scope module not16 $end
$var wire 16 ! in [15:0] $end
$var wire 16 " out [15:0] $end
$scope module not0 $end
$var wire 1 # in $end
$var wire 1 $ out $end
$upscope $end
$scope module not1 $end
$var wire 1 % in $end
$var wire 1 & out $end
$upscope $end
$scope module not2 $end
$var wire 1 ' in $end
$var wire 1 ( out $end
$upscope $end
$scope module not3 $end
$var wire 1 ) in $end
$var wire 1 * out $end
$upscope $end
$scope module not4 $end
$var wire 1 + in $end
$var wire 1 , out $end
$upscope $end
$scope module not5 $end
$var wire 1 - in $end
$var wire 1 . out $end
$upscope $end
$scope module not6 $end
$var wire 1 / in $end
$var wire 1 0 out $end
$upscope $end
$scope module not7 $end
$var wire 1 1 in $end
$var wire 1 2 out $end
$upscope $end
$scope module not8 $end
$var wire 1 3 in $end
$var wire 1 4 out $end
$upscope $end
$scope module not9 $end
$var wire 1 5 in $end
$var wire 1 6 out $end
$upscope $end
$scope module not10 $end
$var wire 1 7 in $end
$var wire 1 8 out $end
$upscope $end
$scope module not11 $end
$var wire 1 9 in $end
$var wire 1 : out $end
$upscope $end
$scope module not12 $end
$var wire 1 ; in $end
$var wire 1 < out $end
$upscope $end
$scope module not13 $end
$var wire 1 = in $end
$var wire 1 > out $end
$upscope $end
$scope module not14 $end
$var wire 1 ? in $end
$var wire 1 @ out $end
$upscope $end
$scope module not15 $end
$var wire 1 A in $end
$var wire 1 B out $end
$upscope $end
$upscope $end
$upscope $end
$enddefinitions $end
#0
$dumpvars
xB
xA
x@
x?
x>
x=
x<
x;
x:
x9
x8
x7
x6
x5
x4
x3
x2
x1
x0
x/
x.
x-
x,
x+
x*
x)
x(
x'
x&
x%
x$
x#
bx "
bx !
$end
#1
1$
1&
1(
1*
1,
1.
10
12
14
16
18
1:
1<
1>
1@
1B
b1111111111111111 "
0#
0%
0'
0)
0+
0-
0/
01
03
05
07
09
0;
0=
0?
0A
b0 !
#2
0$
0&
0(
0*
0,
0.
00
02
04
06
08
0:
0<
0>
0@
0B
b0 "
1#
1%
1'
1)
1+
1-
1/
11
13
15
17
19
1;
1=
1?
1A
b1111111111111111 !
#3
14
16
18
1:
1<
1>
1@
1B
b1111111100000000 "
03
05
07
09
0;
0=
0?
0A
b11111111 !
#4
1$
1&
1(
1*
1,
1.
10
12
04
06
08
0:
0<
0>
0@
0B
b11111111 "
0#
0%
0'
0)
0+
0-
0/
01
13
15
17
19
1;
1=
1?
1A
b1111111100000000 !
#5
0$
0&
0(
0*
1<
1>
1@
1B
b1111000011110000 "
1#
1%
1'
1)
0;
0=
0?
0A
b111100001111 !
#6
1$
1&
1(
1*
0,
0.
00
02
14
16
18
1:
0<
0>
0@
0B
b111100001111 "
0#
0%
0'
0)
1+
1-
1/
11
03
05
07
09
1;
1=
1?
1A
b1111000011110000 !
#7
0$
0&
10
12
04
06
1@
1B
b1100110011001100 "
1#
1%
0/
01
13
15
0?
0A
b11001100110011 !
#8
1$
1&
0(
0*
1,
1.
00
02
14
16
08
0:
1<
1>
0@
0B
b11001100110011 "
0#
0%
1'
1)
0+
0-
1/
11
03
05
17
19
0;
0=
1?
1A
b1100110011001100 !
#9
0$
1*
0,
12
04
1:
0<
1B
b1010101010101010 "
1#
0)
1+
01
13
09
1;
0A
b101010101010101 !
#10
1$
0&
1(
0*
1,
0.
10
02
14
06
18
0:
1<
0>
1@
0B
b101010101010101 "
0#
1%
0'
1)
0+
1-
0/
11
03
15
07
19
0;
1=
0?
1A
b1010101010101010 !
