src/verilog/gate.v
module Not(out, in);

    input in;
    output out;

    nand nand0(out, in, in);

endmodule


module And(out, a, b);

    output out;
    input a, b;
    wire w;

    nand nand0(w, a, b);
    Not not0(out, w);

endmodule


module Or(out, a, b);

    output out;
    input a, b;
    wire w0, w1;

    Not not0(w0, a);
    Not not1(w1, b);
    nand nand0(out, w0, w1);

endmodule


module Xor(out, a, b);

    output out;
    input a, b;
    wire w0, w1, w2;

    nand nand0(w0, a, b);
    nand nand1(w1, a, w0);
    nand nand2(w2, w0, b);
    nand nand3(out, w1, w2);

endmodule


module Or8Way(out, in);

    output out;
    input[7:0] in;
    wire w[5:0];

    Or or0(w0, in[0], in[1]);
    Or or1(w1, in[2], in[3]);
    Or or2(w2, in[4], in[5]);
    Or or3(w3, in[6], in[7]);
    Or or4(w4, w0, w1);
    Or or5(w5, w2, w3);
    Or or6(out, w4, w5);

endmodule

src/verilog/Or16.v
module Or16(out, a, b);

    output[15:0] out;
    input[15:0] a, b;

    Or or0(out[0], a[0], b[0]);
    Or or1(out[1], a[1], b[1]);
    Or or2(out[2], a[2], b[2]);
    Or or3(out[3], a[3], b[3]);
    Or or4(out[4], a[4], b[4]);
    Or or5(out[5], a[5], b[5]);
    Or or6(out[6], a[6], b[6]);
    Or or7(out[7], a[7], b[7]);
    Or or8(out[8], a[8], b[8]);
    Or or9(out[9], a[9], b[9]);
    Or or10(out[10], a[10], b[10]);
    Or or11(out[11], a[11], b[11]);
    Or or12(out[12], a[12], b[12]);
    Or or13(out[13], a[13], b[13]);
    Or or14(out[14], a[14], b[14]);
    Or or15(out[15], a[15], b[15]);

endmodule

src/verilog/Or16_test.v
module Or16_test;

    reg[15:0] a, b;
    wire[15:0] out;

    initial
        begin
            $dumpfile("Or16_test.vcd");
            $dumpvars(0, or16);
            $monitor("a = %b, b = %b, out = %b", a, b, out);

            #1 a = 16'h3800; b = 16'h1c;
            #1 a = 16'h4600; b = 16'h62;
            #1 a = 16'h8100; b = 16'h81;
            #1 a = 16'h8000; b = 16'h1;
            #1 a = 16'h6000; b = 16'h6;
            #1 a = 16'h1800; b = 16'h18;
            #1 a = 16'h600; b = 16'h60;
            #1 a = 16'h100; b = 16'h80;
            #1 a = 16'hff; b = 16'hff00;
            #1 $finish;

        end

    Or16 or16(out, a, b);

endmodule

src/verilog/Or16_test.vcd
$date
	Mon Dec  9 19:35:46 2019
$end
$version
	Icarus Verilog
$end
$timescale
	1s
$end
$scope module Or16_test $end
$scope module or16 $end
$var wire 16 ! a [15:0] $end
$var wire 16 " b [15:0] $end
$var wire 16 # out [15:0] $end
$scope module or0 $end
$var wire 1 $ a $end
$var wire 1 % b $end
$var wire 1 & out $end
$var wire 1 ' w0 $end
$var wire 1 ( w1 $end
$scope module not0 $end
$var wire 1 $ in $end
$var wire 1 ' out $end
$upscope $end
$scope module not1 $end
$var wire 1 % in $end
$var wire 1 ( out $end
$upscope $end
$upscope $end
$scope module or1 $end
$var wire 1 ) a $end
$var wire 1 * b $end
$var wire 1 + out $end
$var wire 1 , w0 $end
$var wire 1 - w1 $end
$scope module not0 $end
$var wire 1 ) in $end
$var wire 1 , out $end
$upscope $end
$scope module not1 $end
$var wire 1 * in $end
$var wire 1 - out $end
$upscope $end
$upscope $end
$scope module or2 $end
$var wire 1 . a $end
$var wire 1 / b $end
$var wire 1 0 out $end
$var wire 1 1 w0 $end
$var wire 1 2 w1 $end
$scope module not0 $end
$var wire 1 . in $end
$var wire 1 1 out $end
$upscope $end
$scope module not1 $end
$var wire 1 / in $end
$var wire 1 2 out $end
$upscope $end
$upscope $end
$scope module or3 $end
$var wire 1 3 a $end
$var wire 1 4 b $end
$var wire 1 5 out $end
$var wire 1 6 w0 $end
$var wire 1 7 w1 $end
$scope module not0 $end
$var wire 1 3 in $end
$var wire 1 6 out $end
$upscope $end
$scope module not1 $end
$var wire 1 4 in $end
$var wire 1 7 out $end
$upscope $end
$upscope $end
$scope module or4 $end
$var wire 1 8 a $end
$var wire 1 9 b $end
$var wire 1 : out $end
$var wire 1 ; w0 $end
$var wire 1 < w1 $end
$scope module not0 $end
$var wire 1 8 in $end
$var wire 1 ; out $end
$upscope $end
$scope module not1 $end
$var wire 1 9 in $end
$var wire 1 < out $end
$upscope $end
$upscope $end
$scope module or5 $end
$var wire 1 = a $end
$var wire 1 > b $end
$var wire 1 ? out $end
$var wire 1 @ w0 $end
$var wire 1 A w1 $end
$scope module not0 $end
$var wire 1 = in $end
$var wire 1 @ out $end
$upscope $end
$scope module not1 $end
$var wire 1 > in $end
$var wire 1 A out $end
$upscope $end
$upscope $end
$scope module or6 $end
$var wire 1 B a $end
$var wire 1 C b $end
$var wire 1 D out $end
$var wire 1 E w0 $end
$var wire 1 F w1 $end
$scope module not0 $end
$var wire 1 B in $end
$var wire 1 E out $end
$upscope $end
$scope module not1 $end
$var wire 1 C in $end
$var wire 1 F out $end
$upscope $end
$upscope $end
$scope module or7 $end
$var wire 1 G a $end
$var wire 1 H b $end
$var wire 1 I out $end
$var wire 1 J w0 $end
$var wire 1 K w1 $end
$scope module not0 $end
$var wire 1 G in $end
$var wire 1 J out $end
$upscope $end
$scope module not1 $end
$var wire 1 H in $end
$var wire 1 K out $end
$upscope $end
$upscope $end
$scope module or8 $end
$var wire 1 L a $end
$var wire 1 M b $end
$var wire 1 N out $end
$var wire 1 O w0 $end
$var wire 1 P w1 $end
$scope module not0 $end
$var wire 1 L in $end
$var wire 1 O out $end
$upscope $end
$scope module not1 $end
$var wire 1 M in $end
$var wire 1 P out $end
$upscope $end
$upscope $end
$scope module or9 $end
$var wire 1 Q a $end
$var wire 1 R b $end
$var wire 1 S out $end
$var wire 1 T w0 $end
$var wire 1 U w1 $end
$scope module not0 $end
$var wire 1 Q in $end
$var wire 1 T out $end
$upscope $end
$scope module not1 $end
$var wire 1 R in $end
$var wire 1 U out $end
$upscope $end
$upscope $end
$scope module or10 $end
$var wire 1 V a $end
$var wire 1 W b $end
$var wire 1 X out $end
$var wire 1 Y w0 $end
$var wire 1 Z w1 $end
$scope module not0 $end
$var wire 1 V in $end
$var wire 1 Y out $end
$upscope $end
$scope module not1 $end
$var wire 1 W in $end
$var wire 1 Z out $end
$upscope $end
$upscope $end
$scope module or11 $end
$var wire 1 [ a $end
$var wire 1 \ b $end
$var wire 1 ] out $end
$var wire 1 ^ w0 $end
$var wire 1 _ w1 $end
$scope module not0 $end
$var wire 1 [ in $end
$var wire 1 ^ out $end
$upscope $end
$scope module not1 $end
$var wire 1 \ in $end
$var wire 1 _ out $end
$upscope $end
$upscope $end
$scope module or12 $end
$var wire 1 ` a $end
$var wire 1 a b $end
$var wire 1 b out $end
$var wire 1 c w0 $end
$var wire 1 d w1 $end
$scope module not0 $end
$var wire 1 ` in $end
$var wire 1 c out $end
$upscope $end
$scope module not1 $end
$var wire 1 a in $end
$var wire 1 d out $end
$upscope $end
$upscope $end
$scope module or13 $end
$var wire 1 e a $end
$var wire 1 f b $end
$var wire 1 g out $end
$var wire 1 h w0 $end
$var wire 1 i w1 $end
$scope module not0 $end
$var wire 1 e in $end
$var wire 1 h out $end
$upscope $end
$scope module not1 $end
$var wire 1 f in $end
$var wire 1 i out $end
$upscope $end
$upscope $end
$scope module or14 $end
$var wire 1 j a $end
$var wire 1 k b $end
$var wire 1 l out $end
$var wire 1 m w0 $end
$var wire 1 n w1 $end
$scope module not0 $end
$var wire 1 j in $end
$var wire 1 m out $end
$upscope $end
$scope module not1 $end
$var wire 1 k in $end
$var wire 1 n out $end
$upscope $end
$upscope $end
$scope module or15 $end
$var wire 1 o a $end
$var wire 1 p b $end
$var wire 1 q out $end
$var wire 1 r w0 $end
$var wire 1 s w1 $end
$scope module not0 $end
$var wire 1 o in $end
$var wire 1 r out $end
$upscope $end
$scope module not1 $end
$var wire 1 p in $end
$var wire 1 s out $end
$upscope $end
$upscope $end
$upscope $end
$upscope $end
$enddefinitions $end
#0
$dumpvars
xs
xr
xq
xp
xo
xn
xm
xl
xk
xj
xi
xh
xg
xf
xe
xd
xc
xb
xa
x`
x_
x^
x]
x\
x[
xZ
xY
xX
xW
xV
xU
xT
xS
xR
xQ
xP
xO
xN
xM
xL
xK
xJ
xI
xH
xG
xF
xE
xD
xC
xB
xA
x@
x?
x>
x=
x<
x;
x:
x9
x8
x7
x6
x5
x4
x3
x2
x1
x0
x/
x.
x-
x,
x+
x*
x)
x(
x'
x&
x%
x$
bx #
bx "
bx !
$end
#1
0&
0+
10
15
1:
0?
0D
0I
0N
0S
0X
1]
1b
1g
0l
0q
b11100000011100 #
1(
1-
02
07
0<
1A
1F
1K
1P
1U
1Z
1_
1d
1i
1n
1s
1'
1,
11
16
1;
1@
1E
1J
1O
1T
1Y
0^
0c
0h
1m
1r
0%
0*
1/
14
19
0>
0C
0H
0M
0R
0W
0\
0a
0f
0k
0p
0$
0)
0.
03
08
0=
0B
0G
0L
0Q
0V
1[
1`
1e
0j
0o
b11100 "
b11100000000000 !
#2
1+
00
05
0:
1?
1D
1S
1X
0]
0b
0g
1l
b100011001100010 #
0-
12
17
1<
0A
0F
0T
0Y
1^
1c
1h
0m
1*
0/
04
09
1>
1C
1Q
1V
0[
0`
0e
1j
b1100010 "
b100011000000000 !
#3
1&
0+
0?
0D
1I
1N
0S
0X
0l
1q
b1000000110000001 #
0(
1-
1A
1F
0K
0O
1T
1Y
1m
0r
1%
0*
0>
0C
1H
1L
0Q
0V
0j
1o
b10000001 "
b1000000100000000 !
#4
0I
0N
b1000000000000001 #
1K
1O
0H
0L
b1 "
b1000000000000000 !
#5
0&
1+
10
1g
1l
0q
b110000000000110 #
1(
0-
02
0h
0m
1r
0%
1*
1/
1e
1j
0o
b110 "
b110000000000000 !
#6
0+
00
15
1:
1]
1b
0g
0l
b1100000011000 #
1-
12
07
0<
0^
0c
1h
1m
0*
0/
14
19
1[
1`
0e
0j
b11000 "
b1100000000000 !
#7
05
0:
1?
1D
1S
1X
0]
0b
b11001100000 #
17
1<
0A
0F
0T
0Y
1^
1c
04
09
1>
1C
1Q
1V
0[
0`
b1100000 "
b11000000000 !
#8
0?
0D
1I
1N
0S
0X
b110000000 #
1A
1F
0K
0O
1T
1Y
0>
0C
1H
1L
0Q
0V
b10000000 "
b100000000 !
#9
1S
1X
1]
1b
1g
1l
1q
1&
1+
10
15
1:
1?
1D
b1111111111111111 #
1K
0P
0U
0Z
0_
0d
0i
0n
0s
0'
0,
01
06
0;
0@
0E
0J
1O
0H
1M
1R
1W
1\
1a
1f
1k
1p
1$
1)
1.
13
18
1=
1B
1G
0L
b1111111100000000 "
b11111111 !
